static_site_containerizer/__init__.py
static_site_containerizer/templates.py
static_site_containerizer-0.2.1.dist-info/LICENSE
static_site_containerizer-0.2.1.dist-info/METADATA
static_site_containerizer-0.2.1.dist-info/WHEEL
static_site_containerizer-0.2.1.dist-info/entry_points.txt
static_site_containerizer-0.2.1.dist-info/RECORD
